belt/__init__.py
belt/apps.py
belt/commands.py
belt/decorators.py
belt/django_filters/__init__.py
belt/django_filters/filters.py
belt/files.py
belt/generators.py
belt/managers.py
belt/models.py
belt/rest_framework/__init__.py
belt/rest_framework/mixins.py
belt/rest_framework/serializers.py
django_belt-1.10.0.dist-info/LICENSE
django_belt-1.10.0.dist-info/METADATA
django_belt-1.10.0.dist-info/WHEEL
django_belt-1.10.0.dist-info/RECORD
