Metadata-Version: 2.1
Name: django-belt
Version: 1.10.0
Summary: Simple package with some utilities for Django.
Home-page: https://github.com/marcosgabarda/django-belt
License: MIT
Author: Marcos Gabarda
Author-email: hey@marcosgabarda.com
Requires-Python: >=3.10,<4.0
Classifier: Environment :: Web Environment
Classifier: Framework :: Django
Classifier: License :: OSI Approved :: MIT License
Classifier: Programming Language :: Python :: 3
Classifier: Programming Language :: Python :: 3.10
Classifier: Programming Language :: Python :: 3.11
Classifier: Topic :: Utilities
Requires-Dist: django (>=3.0.0)
Requires-Dist: django-filter (>=21.1,<22.0)
Requires-Dist: django-model-utils (>=4.1.0,<5.0.0)
Requires-Dist: djangorestframework (>=3.12.0)
Requires-Dist: single-source (>=0.3.0)
